{
  "Id": "816fca47-523b-4133-8495-e08dd96ff654",
  "Name": "EmployeeProfile",
  "OriginalName": "EmployeeProfile",
  "NamePlural": "EmployeeProfiles",
  "DatabaseTableName": "EmployeeProfiles",
  "Namespace": "EmployeeProfiles",
  "BaseClass": "FullAuditedAggregateRoot",
  "MenuIcon": "file-alt",
  "PrimaryKeyType": "Guid",
  "IsMultiTenant": true,
  "CheckConcurrency": true,
  "ShouldCreateUserInterface": true,
  "ShouldCreateBackend": true,
  "ShouldExportExcel": true,
  "ShouldAddMigration": true,
  "ShouldUpdateDatabase": true,
  "CreateTests": true,
  "Properties": [
    {
      "Id": "51c26619-662a-42c6-9f5b-3fc4188e5cb0",
      "Name": "Code",
      "Type": "string",
      "EnumType": "",
      "EnumNamespace": "",
      "EnumAngularImport": "shared/enums",
      "EnumFilePath": null,
      "DefaultValue": null,
      "IsNullable": false,
      "IsRequired": true,
      "IsTextArea": false,
      "MinLength": 1,
      "MaxLength": 20,
      "SortOrder": 0,
      "SortType": 0,
      "Regex": "",
      "EmailValidation": false,
      "EnumValues": null,
      "IsSelected": true,
      "OrdinalIndex": 0
    },
    {
      "Id": "48f05fca-2ad5-4f26-8dc7-85dc2fb0b63b",
      "Name": "ERPCode",
      "Type": "string",
      "EnumType": "",
      "EnumNamespace": "",
      "EnumAngularImport": "shared/enums",
      "EnumFilePath": null,
      "DefaultValue": null,
      "IsNullable": false,
      "IsRequired": false,
      "IsTextArea": false,
      "MinLength": null,
      "MaxLength": null,
      "SortOrder": 0,
      "SortType": 0,
      "Regex": "",
      "EmailValidation": false,
      "EnumValues": null,
      "IsSelected": true,
      "OrdinalIndex": 0
    },
    {
      "Id": "53cfe758-b863-43fb-bf59-ec216ced69c8",
      "Name": "FirstName",
      "Type": "string",
      "EnumType": "",
      "EnumNamespace": "",
      "EnumAngularImport": "shared/enums",
      "EnumFilePath": null,
      "DefaultValue": null,
      "IsNullable": false,
      "IsRequired": true,
      "IsTextArea": false,
      "MinLength": 1,
      "MaxLength": 255,
      "SortOrder": 0,
      "SortType": 0,
      "Regex": "",
      "EmailValidation": false,
      "EnumValues": null,
      "IsSelected": true,
      "OrdinalIndex": 0
    },
    {
      "Id": "6bbf7bf8-2591-4eba-9433-7b4c247fd335",
      "Name": "LastName",
      "Type": "string",
      "EnumType": "",
      "EnumNamespace": "",
      "EnumAngularImport": "shared/enums",
      "EnumFilePath": null,
      "DefaultValue": null,
      "IsNullable": false,
      "IsRequired": false,
      "IsTextArea": false,
      "MinLength": null,
      "MaxLength": null,
      "SortOrder": 0,
      "SortType": 0,
      "Regex": "",
      "EmailValidation": false,
      "EnumValues": null,
      "IsSelected": true,
      "OrdinalIndex": 0
    },
    {
      "Id": "817bedf9-b8cd-446b-9844-560a1adcad50",
      "Name": "DateOfBirth",
      "Type": "DateTime",
      "EnumType": "",
      "EnumNamespace": "",
      "EnumAngularImport": "shared/enums",
      "EnumFilePath": null,
      "DefaultValue": null,
      "IsNullable": true,
      "IsRequired": false,
      "IsTextArea": false,
      "MinLength": null,
      "MaxLength": null,
      "SortOrder": 0,
      "SortType": 0,
      "Regex": "",
      "EmailValidation": false,
      "EnumValues": null,
      "IsSelected": true,
      "OrdinalIndex": 0
    },
    {
      "Id": "0a5fd71c-26d8-4d5d-afdb-01ea45081df3",
      "Name": "IdCardNumber",
      "Type": "string",
      "EnumType": "",
      "EnumNamespace": "",
      "EnumAngularImport": "shared/enums",
      "EnumFilePath": null,
      "DefaultValue": null,
      "IsNullable": false,
      "IsRequired": false,
      "IsTextArea": false,
      "MinLength": null,
      "MaxLength": null,
      "SortOrder": 0,
      "SortType": 0,
      "Regex": "",
      "EmailValidation": false,
      "EnumValues": null,
      "IsSelected": true,
      "OrdinalIndex": 0
    },
    {
      "Id": "ab118fe3-0dd5-4cbd-9f01-6a609078aa0f",
      "Name": "Email",
      "Type": "string",
      "EnumType": "",
      "EnumNamespace": "",
      "EnumAngularImport": "shared/enums",
      "EnumFilePath": null,
      "DefaultValue": null,
      "IsNullable": false,
      "IsRequired": false,
      "IsTextArea": false,
      "MinLength": null,
      "MaxLength": null,
      "SortOrder": 0,
      "SortType": 0,
      "Regex": "",
      "EmailValidation": false,
      "EnumValues": null,
      "IsSelected": true,
      "OrdinalIndex": 0
    },
    {
      "Id": "d468b02f-07a5-4d62-9dd4-619d911ea072",
      "Name": "Phone",
      "Type": "string",
      "EnumType": "",
      "EnumNamespace": "",
      "EnumAngularImport": "shared/enums",
      "EnumFilePath": null,
      "DefaultValue": null,
      "IsNullable": false,
      "IsRequired": false,
      "IsTextArea": false,
      "MinLength": null,
      "MaxLength": null,
      "SortOrder": 0,
      "SortType": 0,
      "Regex": "",
      "EmailValidation": false,
      "EnumValues": null,
      "IsSelected": true,
      "OrdinalIndex": 0
    },
    {
      "Id": "bb7b6cc0-7114-4756-a38b-fe7553787784",
      "Name": "Address",
      "Type": "string",
      "EnumType": "",
      "EnumNamespace": "",
      "EnumAngularImport": "shared/enums",
      "EnumFilePath": null,
      "DefaultValue": null,
      "IsNullable": false,
      "IsRequired": false,
      "IsTextArea": false,
      "MinLength": null,
      "MaxLength": null,
      "SortOrder": 0,
      "SortType": 0,
      "Regex": "",
      "EmailValidation": false,
      "EnumValues": null,
      "IsSelected": true,
      "OrdinalIndex": 0
    },
    {
      "Id": "fa8f09ed-76c2-49d3-85ea-7f6e915b930f",
      "Name": "Active",
      "Type": "bool",
      "EnumType": "",
      "EnumNamespace": "",
      "EnumAngularImport": "shared/enums",
      "EnumFilePath": null,
      "DefaultValue": "false",
      "IsNullable": false,
      "IsRequired": false,
      "IsTextArea": false,
      "MinLength": null,
      "MaxLength": null,
      "SortOrder": 0,
      "SortType": 0,
      "Regex": "",
      "EmailValidation": false,
      "EnumValues": null,
      "IsSelected": true,
      "OrdinalIndex": 0
    },
    {
      "Id": "70efeba6-4cc9-4bc3-bd20-cee9f74e63bb",
      "Name": "EffectiveDate",
      "Type": "DateTime",
      "EnumType": "",
      "EnumNamespace": "",
      "EnumAngularImport": "shared/enums",
      "EnumFilePath": null,
      "DefaultValue": null,
      "IsNullable": true,
      "IsRequired": false,
      "IsTextArea": false,
      "MinLength": null,
      "MaxLength": null,
      "SortOrder": 0,
      "SortType": 0,
      "Regex": "",
      "EmailValidation": false,
      "EnumValues": null,
      "IsSelected": true,
      "OrdinalIndex": 0
    },
    {
      "Id": "343c5000-8112-4ace-8b77-6fdd765fda14",
      "Name": "EndDate",
      "Type": "DateTime",
      "EnumType": "",
      "EnumNamespace": "",
      "EnumAngularImport": "shared/enums",
      "EnumFilePath": null,
      "DefaultValue": null,
      "IsNullable": true,
      "IsRequired": false,
      "IsTextArea": false,
      "MinLength": null,
      "MaxLength": null,
      "SortOrder": 0,
      "SortType": 0,
      "Regex": "",
      "EmailValidation": false,
      "EnumValues": null,
      "IsSelected": true,
      "OrdinalIndex": 0
    },
    {
      "Id": "b447d69e-d3e2-4a01-8406-1fb7ece0adc0",
      "Name": "IdentityUserId",
      "Type": "Guid",
      "EnumType": "",
      "EnumNamespace": "",
      "EnumAngularImport": "shared/enums",
      "EnumFilePath": null,
      "DefaultValue": null,
      "IsNullable": true,
      "IsRequired": false,
      "IsTextArea": false,
      "MinLength": null,
      "MaxLength": null,
      "SortOrder": 0,
      "SortType": 0,
      "Regex": "",
      "EmailValidation": false,
      "EnumValues": null,
      "IsSelected": true,
      "OrdinalIndex": 0
    }
  ],
  "NavigationProperties": [
    {
      "EntityNameWithDuplicationNumber": "WorkingPosition",
      "EntitySetNameWithDuplicationNumber": "WorkingPositions",
      "ReferencePropertyName": "WorkingPosition",
      "UiPickType": "Dropdown",
      "IsRequired": false,
      "Name": "WorkingPositionId",
      "DisplayProperty": "Code",
      "Namespace": "DMSpro.OMS.MdmService.WorkingPositions",
      "EntityName": "WorkingPosition",
      "EntitySetName": "WorkingPositions",
      "DtoNamespace": "DMSpro.OMS.MdmService.WorkingPositions",
      "DtoEntityName": "WorkingPositionDto",
      "Type": "Guid"
    },
    {
      "EntityNameWithDuplicationNumber": "SystemData",
      "EntitySetNameWithDuplicationNumber": "SystemDatas",
      "ReferencePropertyName": "EmployeeType",
      "UiPickType": "Dropdown",
      "IsRequired": false,
      "Name": "EmployeeTypeId",
      "DisplayProperty": "ValueCode",
      "Namespace": "DMSpro.OMS.MdmService.SystemDatas",
      "EntityName": "SystemData",
      "EntitySetName": "SystemDatas",
      "DtoNamespace": "DMSpro.OMS.MdmService.SystemDatas",
      "DtoEntityName": "SystemDataDto",
      "Type": "Guid"
    }
  ],
  "NavigationConnections": [],
  "PhysicalFileName": "EmployeeProfile.json"
}