{
  "Id": "8783fa6a-41e0-48c6-936d-2e7be1405d53",
  "Name": "Route",
  "OriginalName": "Route",
  "NamePlural": "Routes",
  "DatabaseTableName": "Routes",
  "Namespace": "Routes",
  "BaseClass": "FullAuditedAggregateRoot",
  "MenuIcon": "file-alt",
  "PrimaryKeyType": "Guid",
  "IsMultiTenant": true,
  "CheckConcurrency": true,
  "ShouldCreateUserInterface": true,
  "ShouldCreateBackend": true,
  "ShouldExportExcel": true,
  "ShouldAddMigration": true,
  "ShouldUpdateDatabase": true,
  "CreateTests": true,
  "Properties": [
    {
      "Id": "1a8d57b7-5f53-450f-839e-28faced28054",
      "Name": "CheckIn",
      "Type": "bool",
      "EnumType": "",
      "EnumNamespace": "",
      "EnumAngularImport": "shared/enums",
      "EnumFilePath": null,
      "DefaultValue": null,
      "IsNullable": false,
      "IsRequired": false,
      "IsTextArea": false,
      "MinLength": null,
      "MaxLength": null,
      "SortOrder": 0,
      "SortType": 0,
      "Regex": "",
      "EmailValidation": false,
      "EnumValues": null,
      "IsSelected": true,
      "OrdinalIndex": 0
    },
    {
      "Id": "0eee74b2-bcac-46e7-ab7d-eec670412ad7",
      "Name": "CheckOut",
      "Type": "bool",
      "EnumType": "",
      "EnumNamespace": "",
      "EnumAngularImport": "shared/enums",
      "EnumFilePath": null,
      "DefaultValue": null,
      "IsNullable": false,
      "IsRequired": false,
      "IsTextArea": false,
      "MinLength": null,
      "MaxLength": null,
      "SortOrder": 0,
      "SortType": 0,
      "Regex": "",
      "EmailValidation": false,
      "EnumValues": null,
      "IsSelected": true,
      "OrdinalIndex": 0
    },
    {
      "Id": "e0d99910-e903-49c6-b369-87bb0fa7199c",
      "Name": "GPSLock",
      "Type": "bool",
      "EnumType": "",
      "EnumNamespace": "",
      "EnumAngularImport": "shared/enums",
      "EnumFilePath": null,
      "DefaultValue": null,
      "IsNullable": false,
      "IsRequired": false,
      "IsTextArea": false,
      "MinLength": null,
      "MaxLength": null,
      "SortOrder": 0,
      "SortType": 0,
      "Regex": "",
      "EmailValidation": false,
      "EnumValues": null,
      "IsSelected": true,
      "OrdinalIndex": 0
    },
    {
      "Id": "77d122f3-f3ee-4494-8e94-a6774608121e",
      "Name": "OutRoute",
      "Type": "bool",
      "EnumType": "",
      "EnumNamespace": "",
      "EnumAngularImport": "shared/enums",
      "EnumFilePath": null,
      "DefaultValue": null,
      "IsNullable": false,
      "IsRequired": false,
      "IsTextArea": false,
      "MinLength": null,
      "MaxLength": null,
      "SortOrder": 0,
      "SortType": 0,
      "Regex": "",
      "EmailValidation": false,
      "EnumValues": null,
      "IsSelected": true,
      "OrdinalIndex": 0
    }
  ],
  "NavigationProperties": [
    {
      "EntityNameWithDuplicationNumber": "SystemData",
      "EntitySetNameWithDuplicationNumber": "SystemDatas",
      "ReferencePropertyName": "RouteType",
      "UiPickType": "Dropdown",
      "IsRequired": true,
      "Name": "RouteTypeId",
      "DisplayProperty": "ValueCode",
      "Namespace": "DMSpro.OMS.MdmService.SystemDatas",
      "EntityName": "SystemData",
      "EntitySetName": "SystemDatas",
      "DtoNamespace": "DMSpro.OMS.MdmService.SystemDatas",
      "DtoEntityName": "SystemDataDto",
      "Type": "Guid"
    },
    {
      "EntityNameWithDuplicationNumber": "ItemGroup",
      "EntitySetNameWithDuplicationNumber": "ItemGroups",
      "ReferencePropertyName": "ItemGroup",
      "UiPickType": "Dropdown",
      "IsRequired": true,
      "Name": "ItemGroupId",
      "DisplayProperty": "Code",
      "Namespace": "DMSpro.OMS.MdmService.ItemGroups",
      "EntityName": "ItemGroup",
      "EntitySetName": "ItemGroups",
      "DtoNamespace": "DMSpro.OMS.MdmService.ItemGroups",
      "DtoEntityName": "ItemGroupDto",
      "Type": "Guid"
    },
    {
      "EntityNameWithDuplicationNumber": "SalesOrgHierarchy",
      "EntitySetNameWithDuplicationNumber": "SalesOrgHierarchies",
      "ReferencePropertyName": "SalesOrgHierarchy",
      "UiPickType": "Dropdown",
      "IsRequired": true,
      "Name": "SalesOrgHierarchyId",
      "DisplayProperty": "Code",
      "Namespace": "DMSpro.OMS.MdmService.SalesOrgHierarchies",
      "EntityName": "SalesOrgHierarchy",
      "EntitySetName": "SalesOrgHierarchies",
      "DtoNamespace": "DMSpro.OMS.MdmService.SalesOrgHierarchies",
      "DtoEntityName": "SalesOrgHierarchyDto",
      "Type": "Guid"
    }
  ],
  "NavigationConnections": [],
  "PhysicalFileName": "Route.json"
}